[
  {
    "id": "eucalyptus-grandis",
    "popularName": "Eucalipto",
    "scientificName": "Eucalyptus grandis",
    "stratum": "EMERGENTE",
    "succession": "PLACENTA_II",
    "climateCompatibility": ["TROPICAL_UMIDO", "SUBTROPICAL"],
    "waterRequirement": "HIGH",
    "spacingArea": 12,
    "companions": ["banana-prata", "cafe-arabica", "feijao-guandu"],
    "antagonists": ["pinus-elliottii"]
  },
  {
    "id": "acacia-mangium",
    "popularName": "Acacia Mangium",
    "scientificName": "Acacia mangium",
    "stratum": "EMERGENTE",
    "succession": "SECUNDARIA_I",
    "climateCompatibility": ["TROPICAL_UMIDO", "TROPICAL_SECO"],
    "waterRequirement": "MEDIUM",
    "spacingArea": 10,
    "companions": ["inga-edulis", "feijao-guandu", "abobora-moranga"],
    "antagonists": []
  },
  {
    "id": "moringa-oleifera",
    "popularName": "Moringa",
    "scientificName": "Moringa oleifera",
    "stratum": "EMERGENTE",
    "succession": "SECUNDARIA_I",
    "climateCompatibility": ["TROPICAL_SECO", "SEMIARIDO"],
    "waterRequirement": "LOW",
    "spacingArea": 9,
    "companions": ["sisal", "palma-forrageira", "vetiver"],
    "antagonists": []
  },
  {
    "id": "nogueira-peca",
    "popularName": "Nogueira Peca",
    "scientificName": "Carya illinoinensis",
    "stratum": "EMERGENTE",
    "succession": "CLIMAX",
    "climateCompatibility": ["TEMPERADO", "SUBTROPICAL"],
    "waterRequirement": "MEDIUM",
    "spacingArea": 16,
    "companions": ["aveia-preta", "trevo-branco", "macieira"],
    "antagonists": []
  },
  {
    "id": "pinus-elliottii",
    "popularName": "Pinus",
    "scientificName": "Pinus elliottii",
    "stratum": "EMERGENTE",
    "succession": "CLIMAX",
    "climateCompatibility": ["TEMPERADO", "SUBTROPICAL"],
    "waterRequirement": "LOW",
    "spacingArea": 14,
    "companions": ["erva-mate", "trevo-branco"],
    "antagonists": ["eucalyptus-grandis", "cacau"]
  },
  {
    "id": "inga-edulis",
    "popularName": "Inga",
    "scientificName": "Inga edulis",
    "stratum": "ALTO",
    "succession": "SECUNDARIA_I",
    "climateCompatibility": ["TROPICAL_UMIDO", "TROPICAL_SECO", "SUBTROPICAL"],
    "waterRequirement": "MEDIUM",
    "spacingArea": 8,
    "companions": ["cacau", "cafe-arabica", "feijao-guandu"],
    "antagonists": []
  },
  {
    "id": "banana-prata",
    "popularName": "Banana Prata",
    "scientificName": "Musa spp.",
    "stratum": "ALTO",
    "succession": "SECUNDARIA_I",
    "climateCompatibility": ["TROPICAL_UMIDO", "TROPICAL_SECO"],
    "waterRequirement": "MEDIUM",
    "spacingArea": 5,
    "companions": ["eucalyptus-grandis", "cacau", "amendoim-forrageiro"],
    "antagonists": ["sisal"]
  },
  {
    "id": "gliricidia-sepium",
    "popularName": "Gliricidia",
    "scientificName": "Gliricidia sepium",
    "stratum": "ALTO",
    "succession": "PLACENTA_II",
    "climateCompatibility": ["TROPICAL_UMIDO", "TROPICAL_SECO", "SEMIARIDO"],
    "waterRequirement": "LOW",
    "spacingArea": 6,
    "companions": ["feijao-guandu", "milho-crioulo", "acerola"],
    "antagonists": []
  },
  {
    "id": "umbuzeiro",
    "popularName": "Umbuzeiro",
    "scientificName": "Spondias tuberosa",
    "stratum": "ALTO",
    "succession": "CLIMAX",
    "climateCompatibility": ["TROPICAL_SECO", "SEMIARIDO"],
    "waterRequirement": "LOW",
    "spacingArea": 7,
    "companions": ["palma-forrageira", "vetiver", "mandioca"],
    "antagonists": []
  },
  {
    "id": "erva-mate",
    "popularName": "Erva Mate",
    "scientificName": "Ilex paraguariensis",
    "stratum": "ALTO",
    "succession": "CLIMAX",
    "climateCompatibility": ["SUBTROPICAL", "TEMPERADO"],
    "waterRequirement": "MEDIUM",
    "spacingArea": 5,
    "companions": ["macieira", "trevo-branco", "aveia-preta"],
    "antagonists": []
  },
  {
    "id": "cacau",
    "popularName": "Cacau",
    "scientificName": "Theobroma cacao",
    "stratum": "MEDIO",
    "succession": "CLIMAX",
    "climateCompatibility": ["TROPICAL_UMIDO"],
    "waterRequirement": "HIGH",
    "spacingArea": 3,
    "companions": ["banana-prata", "inga-edulis", "cupuacu"],
    "antagonists": ["pinus-elliottii"]
  },
  {
    "id": "cafe-arabica",
    "popularName": "Cafe Arabica",
    "scientificName": "Coffea arabica",
    "stratum": "MEDIO",
    "succession": "CLIMAX",
    "climateCompatibility": ["SUBTROPICAL", "TROPICAL_UMIDO", "TEMPERADO"],
    "waterRequirement": "MEDIUM",
    "spacingArea": 2.5,
    "companions": ["eucalyptus-grandis", "inga-edulis", "banana-prata"],
    "antagonists": []
  },
  {
    "id": "cupuacu",
    "popularName": "Cupuacu",
    "scientificName": "Theobroma grandiflorum",
    "stratum": "MEDIO",
    "succession": "CLIMAX",
    "climateCompatibility": ["TROPICAL_UMIDO"],
    "waterRequirement": "HIGH",
    "spacingArea": 3.5,
    "companions": ["cacau", "banana-prata", "inga-edulis"],
    "antagonists": []
  },
  {
    "id": "mamoeiro",
    "popularName": "Mamoeiro",
    "scientificName": "Carica papaya",
    "stratum": "MEDIO",
    "succession": "SECUNDARIA_I",
    "climateCompatibility": ["TROPICAL_UMIDO", "TROPICAL_SECO", "SUBTROPICAL"],
    "waterRequirement": "MEDIUM",
    "spacingArea": 2,
    "companions": ["mandioca", "amendoim-forrageiro", "abobora-moranga"],
    "antagonists": []
  },
  {
    "id": "acerola",
    "popularName": "Acerola",
    "scientificName": "Malpighia emarginata",
    "stratum": "MEDIO",
    "succession": "SECUNDARIA_I",
    "climateCompatibility": ["TROPICAL_SECO", "SEMIARIDO", "SUBTROPICAL"],
    "waterRequirement": "LOW",
    "spacingArea": 2.25,
    "companions": ["gliricidia-sepium", "vetiver", "sisal"],
    "antagonists": []
  },
  {
    "id": "macieira",
    "popularName": "Macieira",
    "scientificName": "Malus domestica",
    "stratum": "MEDIO",
    "succession": "CLIMAX",
    "climateCompatibility": ["TEMPERADO", "SUBTROPICAL"],
    "waterRequirement": "MEDIUM",
    "spacingArea": 3,
    "companions": ["aveia-preta", "trevo-branco", "erva-mate"],
    "antagonists": []
  },
  {
    "id": "feijao-guandu",
    "popularName": "Feijao Guandu",
    "scientificName": "Cajanus cajan",
    "stratum": "BAIXO",
    "succession": "PLACENTA_I",
    "climateCompatibility": ["TROPICAL_UMIDO", "TROPICAL_SECO", "SEMIARIDO"],
    "waterRequirement": "LOW",
    "spacingArea": 1.2,
    "companions": ["milho-crioulo", "mandioca", "abobora-moranga"],
    "antagonists": []
  },
  {
    "id": "mandioca",
    "popularName": "Mandioca",
    "scientificName": "Manihot esculenta",
    "stratum": "BAIXO",
    "succession": "PLACENTA_II",
    "climateCompatibility": ["TROPICAL_UMIDO", "TROPICAL_SECO", "SEMIARIDO"],
    "waterRequirement": "LOW",
    "spacingArea": 1.1,
    "companions": ["milho-crioulo", "feijao-guandu", "amendoim-forrageiro"],
    "antagonists": []
  },
  {
    "id": "milho-crioulo",
    "popularName": "Milho Crioulo",
    "scientificName": "Zea mays",
    "stratum": "BAIXO",
    "succession": "PLACENTA_I",
    "climateCompatibility": ["TROPICAL_UMIDO", "TROPICAL_SECO", "SEMIARIDO", "TEMPERADO", "SUBTROPICAL"],
    "waterRequirement": "MEDIUM",
    "spacingArea": 1,
    "companions": ["feijao-guandu", "abobora-moranga", "mandioca"],
    "antagonists": []
  },
  {
    "id": "aveia-preta",
    "popularName": "Aveia Preta",
    "scientificName": "Avena strigosa",
    "stratum": "BAIXO",
    "succession": "PLACENTA_I",
    "climateCompatibility": ["TEMPERADO", "SUBTROPICAL"],
    "waterRequirement": "MEDIUM",
    "spacingArea": 0.8,
    "companions": ["trevo-branco", "macieira", "nogueira-peca"],
    "antagonists": []
  },
  {
    "id": "vetiver",
    "popularName": "Vetiver",
    "scientificName": "Chrysopogon zizanioides",
    "stratum": "BAIXO",
    "succession": "SECUNDARIA_I",
    "climateCompatibility": ["TROPICAL_SECO", "SEMIARIDO", "SUBTROPICAL"],
    "waterRequirement": "LOW",
    "spacingArea": 1.4,
    "companions": ["umbuzeiro", "acerola", "palma-forrageira"],
    "antagonists": []
  },
  {
    "id": "sisal",
    "popularName": "Sisal",
    "scientificName": "Agave sisalana",
    "stratum": "BAIXO",
    "succession": "SECUNDARIA_I",
    "climateCompatibility": ["TROPICAL_SECO", "SEMIARIDO"],
    "waterRequirement": "LOW",
    "spacingArea": 1.6,
    "companions": ["moringa-oleifera", "acerola", "palma-forrageira"],
    "antagonists": ["banana-prata"]
  },
  {
    "id": "abacaxi",
    "popularName": "Abacaxi",
    "scientificName": "Ananas comosus",
    "stratum": "RASTEIRO",
    "succession": "SECUNDARIA_I",
    "climateCompatibility": ["TROPICAL_UMIDO", "TROPICAL_SECO", "SEMIARIDO"],
    "waterRequirement": "LOW",
    "spacingArea": 0.6,
    "companions": ["mandioca", "banana-prata", "feijao-guandu"],
    "antagonists": []
  },
  {
    "id": "batata-doce",
    "popularName": "Batata Doce",
    "scientificName": "Ipomoea batatas",
    "stratum": "RASTEIRO",
    "succession": "PLACENTA_I",
    "climateCompatibility": ["TROPICAL_UMIDO", "TROPICAL_SECO", "TEMPERADO", "SUBTROPICAL"],
    "waterRequirement": "MEDIUM",
    "spacingArea": 0.55,
    "companions": ["milho-crioulo", "amendoim-forrageiro", "banana-prata"],
    "antagonists": []
  },
  {
    "id": "amendoim-forrageiro",
    "popularName": "Amendoim Forrageiro",
    "scientificName": "Arachis pintoi",
    "stratum": "RASTEIRO",
    "succession": "PLACENTA_I",
    "climateCompatibility": ["TROPICAL_UMIDO", "TROPICAL_SECO", "SUBTROPICAL"],
    "waterRequirement": "MEDIUM",
    "spacingArea": 0.45,
    "companions": ["banana-prata", "mamoeiro", "mandioca"],
    "antagonists": []
  },
  {
    "id": "abobora-moranga",
    "popularName": "Abobora Moranga",
    "scientificName": "Cucurbita maxima",
    "stratum": "RASTEIRO",
    "succession": "PLACENTA_II",
    "climateCompatibility": ["TROPICAL_UMIDO", "TROPICAL_SECO", "TEMPERADO", "SUBTROPICAL"],
    "waterRequirement": "MEDIUM",
    "spacingArea": 0.7,
    "companions": ["milho-crioulo", "feijao-guandu", "mamoeiro"],
    "antagonists": []
  },
  {
    "id": "palma-forrageira",
    "popularName": "Palma Forrageira",
    "scientificName": "Opuntia ficus-indica",
    "stratum": "RASTEIRO",
    "succession": "SECUNDARIA_I",
    "climateCompatibility": ["SEMIARIDO", "TROPICAL_SECO"],
    "waterRequirement": "LOW",
    "spacingArea": 0.9,
    "companions": ["moringa-oleifera", "umbuzeiro", "vetiver"],
    "antagonists": ["cacau"]
  },
  {
    "id": "trevo-branco",
    "popularName": "Trevo Branco",
    "scientificName": "Trifolium repens",
    "stratum": "RASTEIRO",
    "succession": "PLACENTA_I",
    "climateCompatibility": ["TEMPERADO", "SUBTROPICAL"],
    "waterRequirement": "MEDIUM",
    "spacingArea": 0.35,
    "companions": ["aveia-preta", "macieira", "erva-mate"],
    "antagonists": []
  }
]
